{"within":[{"name":"Buildings.Electrical.Interfaces"}],"class_definition":[{"class_prefixes":{"prefix":"model"},"class_specifier":{"long_class_specifier":{"name":"Impedance","comment":{"string":"\"Partial model representing a generalized impedance\""},"composition":{"protect":["protected"],"element_list":{"element":[{"extends_clause":{"name":{"name":"Buildings.Electrical.Interfaces.Load"},"class_modification":{"argument_list":{"argument":[{"element_modification_or_replaceable":{"prefix":"final","element_modification":{"name":{"name":"linearized"},"modification":{"symbol":"\u003d","expression":{"simple_expression":{"expression1":{"logical_term":{"logical_factor":{"relation":{"expression1":{"terms":[{"factor":{"primarys":[{"simple_primary":"false"}]}}]}}}}}}}},"comment":{}}}},{"element_modification_or_replaceable":{"prefix":"final","element_modification":{"name":{"name":"mode"},"modification":{"symbol":"\u003d","expression":{"simple_expression":{"expression1":{"logical_term":{"logical_factor":{"relation":{"expression1":{"terms":[{"factor":{"primarys":[{"component_reference":{"component":"Buildings.Electrical.Types.Load.FixedZ_steady_state"}}]}}]}}}}}}}},"comment":{}}}},{"element_modification_or_replaceable":{"prefix":"final","element_modification":{"name":{"name":"P_nominal"},"modification":{"class_modification":{"argument_list":{"argument":[{"element_modification_or_replaceable":{"element_modification":{"name":{"name":"fixed"},"modification":{"symbol":"\u003d","expression":{"simple_expression":{"expression1":{"logical_term":{"logical_factor":{"relation":{"expression1":{"terms":[{"factor":{"primarys":[{"simple_primary":"true"}]}}]}}}}}}}},"comment":{}}}}]}},"symbol":"\u003d","expression":{"simple_expression":{"expression1":{"logical_term":{"logical_factor":{"relation":{"expression1":{"terms":[{"factor":{"primarys":[{"simple_primary":"0"}]}}]}}}}}}}},"comment":{}}}},{"element_modification_or_replaceable":{"prefix":"final","element_modification":{"name":{"name":"V_nominal"},"modification":{"class_modification":{"argument_list":{"argument":[{"element_modification_or_replaceable":{"element_modification":{"name":{"name":"fixed"},"modification":{"symbol":"\u003d","expression":{"simple_expression":{"expression1":{"logical_term":{"logical_factor":{"relation":{"expression1":{"terms":[{"factor":{"primarys":[{"simple_primary":"true"}]}}]}}}}}}}},"comment":{}}}}]}},"symbol":"\u003d","expression":{"simple_expression":{"expression1":{"logical_term":{"logical_factor":{"relation":{"expression1":{"terms":[{"factor":{"primarys":[{"simple_primary":"1"}]}}]}}}}}}}},"comment":{}}}}]}}}},{"component_clause":{"type_prefix":{"prefix":" parameter"},"type_specifier":{"specifier":{"name":"Boolean"}},"component_list":{"component_declaration":[{"declaration":{"name":"inductive","modification":{"symbol":"\u003d","expression":{"simple_expression":{"expression1":{"logical_term":{"logical_factor":{"relation":{"expression1":{"terms":[{"factor":{"primarys":[{"simple_primary":"true"}]}}]}}}}}}}}},"comment":{"comment":{"string":"\"If true, the load is inductive, otherwise it is capacitive\""},"annotation":{"prefix":"annotation","annotation":{"argument_list":{"argument":[{"element_modification_or_replaceable":{"element_modification":{"name":{"name":"Evaluate"},"modification":{"symbol":"\u003d","expression":{"simple_expression":{"expression1":{"logical_term":{"logical_factor":{"relation":{"expression1":{"terms":[{"factor":{"primarys":[{"simple_primary":"true"}]}}]}}}}}}}},"comment":{}}}},{"element_modification_or_replaceable":{"element_modification":{"name":{"name":"choices"},"modification":{"class_modification":{"argument_list":{"argument":[{"element_modification_or_replaceable":{"element_modification":{"name":{"name":"choice"},"modification":{"symbol":"\u003d","expression":{"simple_expression":{"expression1":{"logical_term":{"logical_factor":{"relation":{"expression1":{"terms":[{"factor":{"primarys":[{"simple_primary":"true"}]}}]}}}}}}}},"comment":{"string":"\"Inductive\""}}}},{"element_modification_or_replaceable":{"element_modification":{"name":{"name":"choice"},"modification":{"symbol":"\u003d","expression":{"simple_expression":{"expression1":{"logical_term":{"logical_factor":{"relation":{"expression1":{"terms":[{"factor":{"primarys":[{"simple_primary":"false"}]}}]}}}}}}}},"comment":{"string":"\"Capacitive\""}}}},{"element_modification_or_replaceable":{"element_modification":{"name":{"name":"__Dymola_radioButtons"},"modification":{"symbol":"\u003d","expression":{"simple_expression":{"expression1":{"logical_term":{"logical_factor":{"relation":{"expression1":{"terms":[{"factor":{"primarys":[{"simple_primary":"true"}]}}]}}}}}}}},"comment":{}}}}]}}},"comment":{}}}}]}}}}}]}}},{"component_clause":{"type_prefix":{"prefix":" parameter"},"type_specifier":{"specifier":{"name":"Modelica.SIunits.Resistance"}},"component_list":{"component_declaration":[{"declaration":{"name":"R","modification":{"class_modification":{"argument_list":{"argument":[{"element_modification_or_replaceable":{"element_modification":{"name":{"name":"start"},"modification":{"symbol":"\u003d","expression":{"simple_expression":{"expression1":{"logical_term":{"logical_factor":{"relation":{"expression1":{"terms":[{"factor":{"primarys":[{"simple_primary":"1"}]}}]}}}}}}}},"comment":{}}}},{"element_modification_or_replaceable":{"element_modification":{"name":{"name":"min"},"modification":{"symbol":"\u003d","expression":{"simple_expression":{"expression1":{"logical_term":{"logical_factor":{"relation":{"expression1":{"terms":[{"factor":{"primarys":[{"simple_primary":"0"}]}}]}}}}}}}},"comment":{}}}}]}},"symbol":"\u003d","expression":{"simple_expression":{"expression1":{"logical_term":{"logical_factor":{"relation":{"expression1":{"terms":[{"factor":{"primarys":[{"simple_primary":"1"}]}}]}}}}}}}}},"comment":{"comment":{"string":"\"Resistance\""},"annotation":{"prefix":"annotation","annotation":{"argument_list":{"argument":[{"element_modification_or_replaceable":{"element_modification":{"name":{"name":"Dialog"},"modification":{"class_modification":{"argument_list":{"argument":[{"element_modification_or_replaceable":{"element_modification":{"name":{"name":"enable"},"modification":{"symbol":"\u003d","expression":{"simple_expression":{"expression1":{"logical_term":{"logical_factor":{"not":"not","relation":{"expression1":{"terms":[{"factor":{"primarys":[{"component_reference":{"component":"use_R_in"}}]}}]}}}}}}}},"comment":{}}}}]}}},"comment":{}}}}]}}}}}]}}},{"component_clause":{"type_prefix":{"prefix":" parameter"},"type_specifier":{"specifier":{"name":"Modelica.SIunits.Inductance"}},"component_list":{"component_declaration":[{"declaration":{"name":"L","modification":{"class_modification":{"argument_list":{"argument":[{"element_modification_or_replaceable":{"element_modification":{"name":{"name":"start"},"modification":{"symbol":"\u003d","expression":{"simple_expression":{"expression1":{"logical_term":{"logical_factor":{"relation":{"expression1":{"terms":[{"factor":{"primarys":[{"simple_primary":"0"}]}}]}}}}}}}},"comment":{}}}},{"element_modification_or_replaceable":{"element_modification":{"name":{"name":"min"},"modification":{"symbol":"\u003d","expression":{"simple_expression":{"expression1":{"logical_term":{"logical_factor":{"relation":{"expression1":{"terms":[{"factor":{"primarys":[{"simple_primary":"0"}]}}]}}}}}}}},"comment":{}}}}]}},"symbol":"\u003d","expression":{"simple_expression":{"expression1":{"logical_term":{"logical_factor":{"relation":{"expression1":{"terms":[{"factor":{"primarys":[{"simple_primary":"0"}]}}]}}}}}}}}},"comment":{"comment":{"string":"\"Inductance\""},"annotation":{"prefix":"annotation","annotation":{"argument_list":{"argument":[{"element_modification_or_replaceable":{"element_modification":{"name":{"name":"Dialog"},"modification":{"class_modification":{"argument_list":{"argument":[{"element_modification_or_replaceable":{"element_modification":{"name":{"name":"enable"},"modification":{"symbol":"\u003d","expression":{"simple_expression":{"expression1":{"logical_term":{"logical_factor":{"relation":{"expression1":{"terms":[{"factor":{"primarys":[{"component_reference":{"component":"inductive"}}]}}]}}},"logical_relation":"and","logical_factors":[{"relation":{"expression1":{"terms":[{"factor":{"primarys":[{"output_expression_list":{"expression":[{"simple_expression":{"expression1":{"logical_term":{"logical_factor":{"not":"not","relation":{"expression1":{"terms":[{"factor":{"primarys":[{"component_reference":{"component":"use_L_in"}}]}}]}}}}}}}]}}]}}]}}}]}}}}},"comment":{}}}}]}}},"comment":{}}}}]}}}}}]}}},{"component_clause":{"type_prefix":{"prefix":" parameter"},"type_specifier":{"specifier":{"name":"Modelica.SIunits.Capacitance"}},"component_list":{"component_declaration":[{"declaration":{"name":"C","modification":{"class_modification":{"argument_list":{"argument":[{"element_modification_or_replaceable":{"element_modification":{"name":{"name":"start"},"modification":{"symbol":"\u003d","expression":{"simple_expression":{"expression1":{"logical_term":{"logical_factor":{"relation":{"expression1":{"terms":[{"factor":{"primarys":[{"simple_primary":"0"}]}}]}}}}}}}},"comment":{}}}},{"element_modification_or_replaceable":{"element_modification":{"name":{"name":"min"},"modification":{"symbol":"\u003d","expression":{"simple_expression":{"expression1":{"logical_term":{"logical_factor":{"relation":{"expression1":{"terms":[{"factor":{"primarys":[{"simple_primary":"0"}]}}]}}}}}}}},"comment":{}}}}]}},"symbol":"\u003d","expression":{"simple_expression":{"expression1":{"logical_term":{"logical_factor":{"relation":{"expression1":{"terms":[{"factor":{"primarys":[{"simple_primary":"0"}]}}]}}}}}}}}},"comment":{"comment":{"string":"\"Capacitance\""},"annotation":{"prefix":"annotation","annotation":{"argument_list":{"argument":[{"element_modification_or_replaceable":{"element_modification":{"name":{"name":"Dialog"},"modification":{"class_modification":{"argument_list":{"argument":[{"element_modification_or_replaceable":{"element_modification":{"name":{"name":"enable"},"modification":{"symbol":"\u003d","expression":{"simple_expression":{"expression1":{"logical_term":{"logical_factor":{"relation":{"expression1":{"terms":[{"factor":{"primarys":[{"output_expression_list":{"expression":[{"simple_expression":{"expression1":{"logical_term":{"logical_factor":{"not":"not","relation":{"expression1":{"terms":[{"factor":{"primarys":[{"component_reference":{"component":"inductive"}}]}}]}}}}}}}]}}]}}]}}},"logical_relation":"and","logical_factors":[{"relation":{"expression1":{"terms":[{"factor":{"primarys":[{"output_expression_list":{"expression":[{"simple_expression":{"expression1":{"logical_term":{"logical_factor":{"not":"not","relation":{"expression1":{"terms":[{"factor":{"primarys":[{"component_reference":{"component":"use_C_in"}}]}}]}}}}}}}]}}]}}]}}}]}}}}},"comment":{}}}}]}}},"comment":{}}}}]}}}}}]}}},{"component_clause":{"type_prefix":{"prefix":" parameter"},"type_specifier":{"specifier":{"name":"Boolean"}},"component_list":{"component_declaration":[{"declaration":{"name":"use_R_in","modification":{"symbol":"\u003d","expression":{"simple_expression":{"expression1":{"logical_term":{"logical_factor":{"relation":{"expression1":{"terms":[{"factor":{"primarys":[{"simple_primary":"false"}]}}]}}}}}}}}},"comment":{"comment":{"string":"\"If true, R is specified by an input\""},"annotation":{"prefix":"annotation","annotation":{"argument_list":{"argument":[{"element_modification_or_replaceable":{"element_modification":{"name":{"name":"Evaluate"},"modification":{"symbol":"\u003d","expression":{"simple_expression":{"expression1":{"logical_term":{"logical_factor":{"relation":{"expression1":{"terms":[{"factor":{"primarys":[{"simple_primary":"true"}]}}]}}}}}}}},"comment":{}}}},{"element_modification_or_replaceable":{"element_modification":{"name":{"name":"Dialog"},"modification":{"class_modification":{"argument_list":{"argument":[{"element_modification_or_replaceable":{"element_modification":{"name":{"name":"tab"},"modification":{"symbol":"\u003d","expression":{"simple_expression":{"expression1":{"logical_term":{"logical_factor":{"relation":{"expression1":{"terms":[{"factor":{"primarys":[{"simple_primary":"\"Variable load\""}]}}]}}}}}}}},"comment":{}}}},{"element_modification_or_replaceable":{"element_modification":{"name":{"name":"group"},"modification":{"symbol":"\u003d","expression":{"simple_expression":{"expression1":{"logical_term":{"logical_factor":{"relation":{"expression1":{"terms":[{"factor":{"primarys":[{"simple_primary":"\"Resistance\""}]}}]}}}}}}}},"comment":{}}}}]}}},"comment":{}}}}]}}}}}]}}},{"component_clause":{"type_prefix":{"prefix":" parameter"},"type_specifier":{"specifier":{"name":"Modelica.SIunits.Resistance"}},"component_list":{"component_declaration":[{"declaration":{"name":"RMin","modification":{"class_modification":{"argument_list":{"argument":[{"element_modification_or_replaceable":{"element_modification":{"name":{"name":"start"},"modification":{"symbol":"\u003d","expression":{"simple_expression":{"expression1":{"logical_term":{"logical_factor":{"relation":{"expression1":{"terms":[{"factor":{"primarys":[{"component_reference":{"component":"R"}}]}}]}}}}}}}},"comment":{}}}},{"element_modification_or_replaceable":{"element_modification":{"name":{"name":"min"},"modification":{"symbol":"\u003d","expression":{"simple_expression":{"expression1":{"logical_term":{"logical_factor":{"relation":{"expression1":{"terms":[{"factor":{"primarys":[{"component_reference":{"component":"Modelica.Constants.eps"}}]}}]}}}}}}}},"comment":{}}}}]}},"symbol":"\u003d","expression":{"simple_expression":{"expression1":{"logical_term":{"logical_factor":{"relation":{"expression1":{"terms":[{"factor":{"primarys":[{"simple_primary":"1e-4"}]}}]}}}}}}}}},"comment":{"comment":{"string":"\"Minimum value of the resistance\""},"annotation":{"prefix":"annotation","annotation":{"argument_list":{"argument":[{"element_modification_or_replaceable":{"element_modification":{"name":{"name":"Evaluate"},"modification":{"symbol":"\u003d","expression":{"simple_expression":{"expression1":{"logical_term":{"logical_factor":{"relation":{"expression1":{"terms":[{"factor":{"primarys":[{"simple_primary":"true"}]}}]}}}}}}}},"comment":{}}}},{"element_modification_or_replaceable":{"element_modification":{"name":{"name":"Dialog"},"modification":{"class_modification":{"argument_list":{"argument":[{"element_modification_or_replaceable":{"element_modification":{"name":{"name":"enable"},"modification":{"symbol":"\u003d","expression":{"simple_expression":{"expression1":{"logical_term":{"logical_factor":{"relation":{"expression1":{"terms":[{"factor":{"primarys":[{"component_reference":{"component":"use_R_in"}}]}}]}}}}}}}},"comment":{}}}},{"element_modification_or_replaceable":{"element_modification":{"name":{"name":"tab"},"modification":{"symbol":"\u003d","expression":{"simple_expression":{"expression1":{"logical_term":{"logical_factor":{"relation":{"expression1":{"terms":[{"factor":{"primarys":[{"simple_primary":"\"Variable load\""}]}}]}}}}}}}},"comment":{}}}},{"element_modification_or_replaceable":{"element_modification":{"name":{"name":"group"},"modification":{"symbol":"\u003d","expression":{"simple_expression":{"expression1":{"logical_term":{"logical_factor":{"relation":{"expression1":{"terms":[{"factor":{"primarys":[{"simple_primary":"\"Resistance\""}]}}]}}}}}}}},"comment":{}}}}]}}},"comment":{}}}}]}}}}}]}}},{"component_clause":{"type_prefix":{"prefix":" parameter"},"type_specifier":{"specifier":{"name":"Modelica.SIunits.Resistance"}},"component_list":{"component_declaration":[{"declaration":{"name":"RMax","modification":{"class_modification":{"argument_list":{"argument":[{"element_modification_or_replaceable":{"element_modification":{"name":{"name":"start"},"modification":{"symbol":"\u003d","expression":{"simple_expression":{"expression1":{"logical_term":{"logical_factor":{"relation":{"expression1":{"terms":[{"factor":{"primarys":[{"component_reference":{"component":"R"}}]}}]}}}}}}}},"comment":{}}}},{"element_modification_or_replaceable":{"element_modification":{"name":{"name":"min"},"modification":{"symbol":"\u003d","expression":{"simple_expression":{"expression1":{"logical_term":{"logical_factor":{"relation":{"expression1":{"terms":[{"factor":{"primarys":[{"component_reference":{"component":"Modelica.Constants.eps"}}]}}]}}}}}}}},"comment":{}}}}]}},"symbol":"\u003d","expression":{"simple_expression":{"expression1":{"logical_term":{"logical_factor":{"relation":{"expression1":{"terms":[{"factor":{"primarys":[{"simple_primary":"1e2"}]}}]}}}}}}}}},"comment":{"comment":{"string":"\"Maximum value of the resistance\""},"annotation":{"prefix":"annotation","annotation":{"argument_list":{"argument":[{"element_modification_or_replaceable":{"element_modification":{"name":{"name":"Evaluate"},"modification":{"symbol":"\u003d","expression":{"simple_expression":{"expression1":{"logical_term":{"logical_factor":{"relation":{"expression1":{"terms":[{"factor":{"primarys":[{"simple_primary":"true"}]}}]}}}}}}}},"comment":{}}}},{"element_modification_or_replaceable":{"element_modification":{"name":{"name":"Dialog"},"modification":{"class_modification":{"argument_list":{"argument":[{"element_modification_or_replaceable":{"element_modification":{"name":{"name":"enable"},"modification":{"symbol":"\u003d","expression":{"simple_expression":{"expression1":{"logical_term":{"logical_factor":{"relation":{"expression1":{"terms":[{"factor":{"primarys":[{"component_reference":{"component":"use_R_in"}}]}}]}}}}}}}},"comment":{}}}},{"element_modification_or_replaceable":{"element_modification":{"name":{"name":"tab"},"modification":{"symbol":"\u003d","expression":{"simple_expression":{"expression1":{"logical_term":{"logical_factor":{"relation":{"expression1":{"terms":[{"factor":{"primarys":[{"simple_primary":"\"Variable load\""}]}}]}}}}}}}},"comment":{}}}},{"element_modification_or_replaceable":{"element_modification":{"name":{"name":"group"},"modification":{"symbol":"\u003d","expression":{"simple_expression":{"expression1":{"logical_term":{"logical_factor":{"relation":{"expression1":{"terms":[{"factor":{"primarys":[{"simple_primary":"\"Resistance\""}]}}]}}}}}}}},"comment":{}}}}]}}},"comment":{}}}}]}}}}}]}}},{"component_clause":{"type_prefix":{"prefix":" parameter"},"type_specifier":{"specifier":{"name":"Boolean"}},"component_list":{"component_declaration":[{"declaration":{"name":"use_C_in","modification":{"symbol":"\u003d","expression":{"simple_expression":{"expression1":{"logical_term":{"logical_factor":{"relation":{"expression1":{"terms":[{"factor":{"primarys":[{"simple_primary":"false"}]}}]}}}}}}}}},"comment":{"comment":{"string":"\"If true, C is specified by an input\""},"annotation":{"prefix":"annotation","annotation":{"argument_list":{"argument":[{"element_modification_or_replaceable":{"element_modification":{"name":{"name":"Evaluate"},"modification":{"symbol":"\u003d","expression":{"simple_expression":{"expression1":{"logical_term":{"logical_factor":{"relation":{"expression1":{"terms":[{"factor":{"primarys":[{"simple_primary":"true"}]}}]}}}}}}}},"comment":{}}}},{"element_modification_or_replaceable":{"element_modification":{"name":{"name":"Dialog"},"modification":{"class_modification":{"argument_list":{"argument":[{"element_modification_or_replaceable":{"element_modification":{"name":{"name":"tab"},"modification":{"symbol":"\u003d","expression":{"simple_expression":{"expression1":{"logical_term":{"logical_factor":{"relation":{"expression1":{"terms":[{"factor":{"primarys":[{"simple_primary":"\"Variable load\""}]}}]}}}}}}}},"comment":{}}}},{"element_modification_or_replaceable":{"element_modification":{"name":{"name":"group"},"modification":{"symbol":"\u003d","expression":{"simple_expression":{"expression1":{"logical_term":{"logical_factor":{"relation":{"expression1":{"terms":[{"factor":{"primarys":[{"simple_primary":"\"Capacitance\""}]}}]}}}}}}}},"comment":{}}}}]}}},"comment":{}}}}]}}}}}]}}},{"component_clause":{"type_prefix":{"prefix":" parameter"},"type_specifier":{"specifier":{"name":"Modelica.SIunits.Capacitance"}},"component_list":{"component_declaration":[{"declaration":{"name":"CMin","modification":{"class_modification":{"argument_list":{"argument":[{"element_modification_or_replaceable":{"element_modification":{"name":{"name":"start"},"modification":{"symbol":"\u003d","expression":{"simple_expression":{"expression1":{"logical_term":{"logical_factor":{"relation":{"expression1":{"terms":[{"factor":{"primarys":[{"component_reference":{"component":"C"}}]}}]}}}}}}}},"comment":{}}}},{"element_modification_or_replaceable":{"element_modification":{"name":{"name":"min"},"modification":{"symbol":"\u003d","expression":{"simple_expression":{"expression1":{"logical_term":{"logical_factor":{"relation":{"expression1":{"terms":[{"factor":{"primarys":[{"component_reference":{"component":"Modelica.Constants.eps"}}]}}]}}}}}}}},"comment":{}}}}]}},"symbol":"\u003d","expression":{"simple_expression":{"expression1":{"logical_term":{"logical_factor":{"relation":{"expression1":{"terms":[{"factor":{"primarys":[{"simple_primary":"1e-4"}]}}]}}}}}}}}},"comment":{"comment":{"string":"\"Minimum value of the capacitance\""},"annotation":{"prefix":"annotation","annotation":{"argument_list":{"argument":[{"element_modification_or_replaceable":{"element_modification":{"name":{"name":"Evaluate"},"modification":{"symbol":"\u003d","expression":{"simple_expression":{"expression1":{"logical_term":{"logical_factor":{"relation":{"expression1":{"terms":[{"factor":{"primarys":[{"simple_primary":"true"}]}}]}}}}}}}},"comment":{}}}},{"element_modification_or_replaceable":{"element_modification":{"name":{"name":"Dialog"},"modification":{"class_modification":{"argument_list":{"argument":[{"element_modification_or_replaceable":{"element_modification":{"name":{"name":"enable"},"modification":{"symbol":"\u003d","expression":{"simple_expression":{"expression1":{"logical_term":{"logical_factor":{"relation":{"expression1":{"terms":[{"factor":{"primarys":[{"component_reference":{"component":"use_C_in"}}]}}]}}}}}}}},"comment":{}}}},{"element_modification_or_replaceable":{"element_modification":{"name":{"name":"tab"},"modification":{"symbol":"\u003d","expression":{"simple_expression":{"expression1":{"logical_term":{"logical_factor":{"relation":{"expression1":{"terms":[{"factor":{"primarys":[{"simple_primary":"\"Variable load\""}]}}]}}}}}}}},"comment":{}}}},{"element_modification_or_replaceable":{"element_modification":{"name":{"name":"group"},"modification":{"symbol":"\u003d","expression":{"simple_expression":{"expression1":{"logical_term":{"logical_factor":{"relation":{"expression1":{"terms":[{"factor":{"primarys":[{"simple_primary":"\"Capacitance\""}]}}]}}}}}}}},"comment":{}}}}]}}},"comment":{}}}}]}}}}}]}}},{"component_clause":{"type_prefix":{"prefix":" parameter"},"type_specifier":{"specifier":{"name":"Modelica.SIunits.Capacitance"}},"component_list":{"component_declaration":[{"declaration":{"name":"CMax","modification":{"class_modification":{"argument_list":{"argument":[{"element_modification_or_replaceable":{"element_modification":{"name":{"name":"start"},"modification":{"symbol":"\u003d","expression":{"simple_expression":{"expression1":{"logical_term":{"logical_factor":{"relation":{"expression1":{"terms":[{"factor":{"primarys":[{"component_reference":{"component":"C"}}]}}]}}}}}}}},"comment":{}}}},{"element_modification_or_replaceable":{"element_modification":{"name":{"name":"min"},"modification":{"symbol":"\u003d","expression":{"simple_expression":{"expression1":{"logical_term":{"logical_factor":{"relation":{"expression1":{"terms":[{"factor":{"primarys":[{"component_reference":{"component":"Modelica.Constants.eps"}}]}}]}}}}}}}},"comment":{}}}}]}},"symbol":"\u003d","expression":{"simple_expression":{"expression1":{"logical_term":{"logical_factor":{"relation":{"expression1":{"terms":[{"factor":{"primarys":[{"simple_primary":"1e2"}]}}]}}}}}}}}},"comment":{"comment":{"string":"\"Maximum value of the capacitance\""},"annotation":{"prefix":"annotation","annotation":{"argument_list":{"argument":[{"element_modification_or_replaceable":{"element_modification":{"name":{"name":"Evaluate"},"modification":{"symbol":"\u003d","expression":{"simple_expression":{"expression1":{"logical_term":{"logical_factor":{"relation":{"expression1":{"terms":[{"factor":{"primarys":[{"simple_primary":"true"}]}}]}}}}}}}},"comment":{}}}},{"element_modification_or_replaceable":{"element_modification":{"name":{"name":"Dialog"},"modification":{"class_modification":{"argument_list":{"argument":[{"element_modification_or_replaceable":{"element_modification":{"name":{"name":"enable"},"modification":{"symbol":"\u003d","expression":{"simple_expression":{"expression1":{"logical_term":{"logical_factor":{"relation":{"expression1":{"terms":[{"factor":{"primarys":[{"component_reference":{"component":"use_C_in"}}]}}]}}}}}}}},"comment":{}}}},{"element_modification_or_replaceable":{"element_modification":{"name":{"name":"tab"},"modification":{"symbol":"\u003d","expression":{"simple_expression":{"expression1":{"logical_term":{"logical_factor":{"relation":{"expression1":{"terms":[{"factor":{"primarys":[{"simple_primary":"\"Variable load\""}]}}]}}}}}}}},"comment":{}}}},{"element_modification_or_replaceable":{"element_modification":{"name":{"name":"group"},"modification":{"symbol":"\u003d","expression":{"simple_expression":{"expression1":{"logical_term":{"logical_factor":{"relation":{"expression1":{"terms":[{"factor":{"primarys":[{"simple_primary":"\"Capacitance\""}]}}]}}}}}}}},"comment":{}}}}]}}},"comment":{}}}}]}}}}}]}}},{"component_clause":{"type_prefix":{"prefix":" parameter"},"type_specifier":{"specifier":{"name":"Boolean"}},"component_list":{"component_declaration":[{"declaration":{"name":"use_L_in","modification":{"symbol":"\u003d","expression":{"simple_expression":{"expression1":{"logical_term":{"logical_factor":{"relation":{"expression1":{"terms":[{"factor":{"primarys":[{"simple_primary":"false"}]}}]}}}}}}}}},"comment":{"comment":{"string":"\"If true, L is specified by an input\""},"annotation":{"prefix":"annotation","annotation":{"argument_list":{"argument":[{"element_modification_or_replaceable":{"element_modification":{"name":{"name":"Evaluate"},"modification":{"symbol":"\u003d","expression":{"simple_expression":{"expression1":{"logical_term":{"logical_factor":{"relation":{"expression1":{"terms":[{"factor":{"primarys":[{"simple_primary":"true"}]}}]}}}}}}}},"comment":{}}}},{"element_modification_or_replaceable":{"element_modification":{"name":{"name":"Dialog"},"modification":{"class_modification":{"argument_list":{"argument":[{"element_modification_or_replaceable":{"element_modification":{"name":{"name":"tab"},"modification":{"symbol":"\u003d","expression":{"simple_expression":{"expression1":{"logical_term":{"logical_factor":{"relation":{"expression1":{"terms":[{"factor":{"primarys":[{"simple_primary":"\"Variable load\""}]}}]}}}}}}}},"comment":{}}}},{"element_modification_or_replaceable":{"element_modification":{"name":{"name":"group"},"modification":{"symbol":"\u003d","expression":{"simple_expression":{"expression1":{"logical_term":{"logical_factor":{"relation":{"expression1":{"terms":[{"factor":{"primarys":[{"simple_primary":"\"Inductance\""}]}}]}}}}}}}},"comment":{}}}}]}}},"comment":{}}}}]}}}}}]}}},{"component_clause":{"type_prefix":{"prefix":" parameter"},"type_specifier":{"specifier":{"name":"Modelica.SIunits.Inductance"}},"component_list":{"component_declaration":[{"declaration":{"name":"LMin","modification":{"class_modification":{"argument_list":{"argument":[{"element_modification_or_replaceable":{"element_modification":{"name":{"name":"start"},"modification":{"symbol":"\u003d","expression":{"simple_expression":{"expression1":{"logical_term":{"logical_factor":{"relation":{"expression1":{"terms":[{"factor":{"primarys":[{"component_reference":{"component":"L"}}]}}]}}}}}}}},"comment":{}}}},{"element_modification_or_replaceable":{"element_modification":{"name":{"name":"min"},"modification":{"symbol":"\u003d","expression":{"simple_expression":{"expression1":{"logical_term":{"logical_factor":{"relation":{"expression1":{"terms":[{"factor":{"primarys":[{"component_reference":{"component":"Modelica.Constants.eps"}}]}}]}}}}}}}},"comment":{}}}}]}},"symbol":"\u003d","expression":{"simple_expression":{"expression1":{"logical_term":{"logical_factor":{"relation":{"expression1":{"terms":[{"factor":{"primarys":[{"simple_primary":"1e-4"}]}}]}}}}}}}}},"comment":{"comment":{"string":"\"Minimum value of the inductance\""},"annotation":{"prefix":"annotation","annotation":{"argument_list":{"argument":[{"element_modification_or_replaceable":{"element_modification":{"name":{"name":"Evaluate"},"modification":{"symbol":"\u003d","expression":{"simple_expression":{"expression1":{"logical_term":{"logical_factor":{"relation":{"expression1":{"terms":[{"factor":{"primarys":[{"simple_primary":"true"}]}}]}}}}}}}},"comment":{}}}},{"element_modification_or_replaceable":{"element_modification":{"name":{"name":"Dialog"},"modification":{"class_modification":{"argument_list":{"argument":[{"element_modification_or_replaceable":{"element_modification":{"name":{"name":"enable"},"modification":{"symbol":"\u003d","expression":{"simple_expression":{"expression1":{"logical_term":{"logical_factor":{"relation":{"expression1":{"terms":[{"factor":{"primarys":[{"component_reference":{"component":"use_L_in"}}]}}]}}}}}}}},"comment":{}}}},{"element_modification_or_replaceable":{"element_modification":{"name":{"name":"tab"},"modification":{"symbol":"\u003d","expression":{"simple_expression":{"expression1":{"logical_term":{"logical_factor":{"relation":{"expression1":{"terms":[{"factor":{"primarys":[{"simple_primary":"\"Variable load\""}]}}]}}}}}}}},"comment":{}}}},{"element_modification_or_replaceable":{"element_modification":{"name":{"name":"group"},"modification":{"symbol":"\u003d","expression":{"simple_expression":{"expression1":{"logical_term":{"logical_factor":{"relation":{"expression1":{"terms":[{"factor":{"primarys":[{"simple_primary":"\"Inductance\""}]}}]}}}}}}}},"comment":{}}}}]}}},"comment":{}}}}]}}}}}]}}},{"component_clause":{"type_prefix":{"prefix":" parameter"},"type_specifier":{"specifier":{"name":"Modelica.SIunits.Inductance"}},"component_list":{"component_declaration":[{"declaration":{"name":"LMax","modification":{"class_modification":{"argument_list":{"argument":[{"element_modification_or_replaceable":{"element_modification":{"name":{"name":"start"},"modification":{"symbol":"\u003d","expression":{"simple_expression":{"expression1":{"logical_term":{"logical_factor":{"relation":{"expression1":{"terms":[{"factor":{"primarys":[{"component_reference":{"component":"L"}}]}}]}}}}}}}},"comment":{}}}},{"element_modification_or_replaceable":{"element_modification":{"name":{"name":"min"},"modification":{"symbol":"\u003d","expression":{"simple_expression":{"expression1":{"logical_term":{"logical_factor":{"relation":{"expression1":{"terms":[{"factor":{"primarys":[{"component_reference":{"component":"Modelica.Constants.eps"}}]}}]}}}}}}}},"comment":{}}}}]}},"symbol":"\u003d","expression":{"simple_expression":{"expression1":{"logical_term":{"logical_factor":{"relation":{"expression1":{"terms":[{"factor":{"primarys":[{"simple_primary":"1e2"}]}}]}}}}}}}}},"comment":{"comment":{"string":"\"Maximum value of the inductance\""},"annotation":{"prefix":"annotation","annotation":{"argument_list":{"argument":[{"element_modification_or_replaceable":{"element_modification":{"name":{"name":"Evaluate"},"modification":{"symbol":"\u003d","expression":{"simple_expression":{"expression1":{"logical_term":{"logical_factor":{"relation":{"expression1":{"terms":[{"factor":{"primarys":[{"simple_primary":"true"}]}}]}}}}}}}},"comment":{}}}},{"element_modification_or_replaceable":{"element_modification":{"name":{"name":"Dialog"},"modification":{"class_modification":{"argument_list":{"argument":[{"element_modification_or_replaceable":{"element_modification":{"name":{"name":"enable"},"modification":{"symbol":"\u003d","expression":{"simple_expression":{"expression1":{"logical_term":{"logical_factor":{"relation":{"expression1":{"terms":[{"factor":{"primarys":[{"component_reference":{"component":"use_L_in"}}]}}]}}}}}}}},"comment":{}}}},{"element_modification_or_replaceable":{"element_modification":{"name":{"name":"tab"},"modification":{"symbol":"\u003d","expression":{"simple_expression":{"expression1":{"logical_term":{"logical_factor":{"relation":{"expression1":{"terms":[{"factor":{"primarys":[{"simple_primary":"\"Variable load\""}]}}]}}}}}}}},"comment":{}}}},{"element_modification_or_replaceable":{"element_modification":{"name":{"name":"group"},"modification":{"symbol":"\u003d","expression":{"simple_expression":{"expression1":{"logical_term":{"logical_factor":{"relation":{"expression1":{"terms":[{"factor":{"primarys":[{"simple_primary":"\"Inductance\""}]}}]}}}}}}}},"comment":{}}}}]}}},"comment":{}}}}]}}}}}]}}},{"component_clause":{"type_prefix":{},"type_specifier":{"specifier":{"name":"Modelica.Blocks.Interfaces.RealInput"}},"component_list":{"component_declaration":[{"declaration":{"name":"y_R","modification":{"class_modification":{"argument_list":{"argument":[{"element_modification_or_replaceable":{"element_modification":{"name":{"name":"min"},"modification":{"symbol":"\u003d","expression":{"simple_expression":{"expression1":{"logical_term":{"logical_factor":{"relation":{"expression1":{"terms":[{"factor":{"primarys":[{"simple_primary":"0"}]}}]}}}}}}}},"comment":{}}}},{"element_modification_or_replaceable":{"element_modification":{"name":{"name":"max"},"modification":{"symbol":"\u003d","expression":{"simple_expression":{"expression1":{"logical_term":{"logical_factor":{"relation":{"expression1":{"terms":[{"factor":{"primarys":[{"simple_primary":"1"}]}}]}}}}}}}},"comment":{}}}}]}}}},"condition_attribute":{"iF":"if","expression":{"simple_expression":{"expression1":{"logical_term":{"logical_factor":{"relation":{"expression1":{"terms":[{"factor":{"primarys":[{"component_reference":{"component":"use_R_in"}}]}}]}}}}}}}},"comment":{"comment":{"string":"\"Input that sepecify variable R\""},"annotation":{"prefix":"annotation","annotation":{"argument_list":{"argument":[{"element_modification_or_replaceable":{"element_modification":{"name":{"name":"Placement"},"modification":{"class_modification":{"argument_list":{"argument":[{"element_modification_or_replaceable":{"element_modification":{"name":{"name":"transformation"},"modification":{"class_modification":{"argument_list":{"argument":[{"element_modification_or_replaceable":{"element_modification":{"name":{"name":"extent"},"modification":{"symbol":"\u003d","expression":{"simple_expression":{"expression1":{"logical_term":{"logical_factor":{"relation":{"expression1":{"terms":[{"factor":{"primarys":[{"function_arguments":{"argument":{"expressions":{"simple_expression":{"expression1":{"logical_term":{"logical_factor":{"relation":{"expression1":{"terms":[{"factor":{"primarys":[{"function_arguments":{"argument":{"expressions":{"simple_expression":{"expression1":{"logical_term":{"logical_factor":{"relation":{"expression1":{"add_pre":{"add_op":"-"},"terms":[{"factor":{"primarys":[{"simple_primary":"20"}]}}]}}}}}}}},"arguments":{"argument":{"expressions":{"simple_expression":{"expression1":{"logical_term":{"logical_factor":{"relation":{"expression1":{"add_pre":{"add_op":"-"},"terms":[{"factor":{"primarys":[{"simple_primary":"20"}]}}]}}}}}}}}}}}]}}]}}}}}}}},"arguments":{"argument":{"expressions":{"simple_expression":{"expression1":{"logical_term":{"logical_factor":{"relation":{"expression1":{"terms":[{"factor":{"primarys":[{"function_arguments":{"argument":{"expressions":{"simple_expression":{"expression1":{"logical_term":{"logical_factor":{"relation":{"expression1":{"terms":[{"factor":{"primarys":[{"simple_primary":"20"}]}}]}}}}}}}},"arguments":{"argument":{"expressions":{"simple_expression":{"expression1":{"logical_term":{"logical_factor":{"relation":{"expression1":{"terms":[{"factor":{"primarys":[{"simple_primary":"20"}]}}]}}}}}}}}}}}]}}]}}}}}}}}}}}]}}]}}}}}}}},"comment":{}}}},{"element_modification_or_replaceable":{"element_modification":{"name":{"name":"rotation"},"modification":{"symbol":"\u003d","expression":{"simple_expression":{"expression1":{"logical_term":{"logical_factor":{"relation":{"expression1":{"terms":[{"factor":{"primarys":[{"simple_primary":"270"}]}}]}}}}}}}},"comment":{}}}},{"element_modification_or_replaceable":{"element_modification":{"name":{"name":"origin"},"modification":{"symbol":"\u003d","expression":{"simple_expression":{"expression1":{"logical_term":{"logical_factor":{"relation":{"expression1":{"terms":[{"factor":{"primarys":[{"function_arguments":{"argument":{"expressions":{"simple_expression":{"expression1":{"logical_term":{"logical_factor":{"relation":{"expression1":{"add_pre":{"add_op":"-"},"terms":[{"factor":{"primarys":[{"simple_primary":"40"}]}}]}}}}}}}},"arguments":{"argument":{"expressions":{"simple_expression":{"expression1":{"logical_term":{"logical_factor":{"relation":{"expression1":{"terms":[{"factor":{"primarys":[{"simple_primary":"100"}]}}]}}}}}}}}}}}]}}]}}}}}}}},"comment":{}}}}]}}},"comment":{}}}}]}}},"comment":{}}}}]}}}}}]}}},{"component_clause":{"type_prefix":{},"type_specifier":{"specifier":{"name":"Modelica.Blocks.Interfaces.RealInput"}},"component_list":{"component_declaration":[{"declaration":{"name":"y_C","modification":{"class_modification":{"argument_list":{"argument":[{"element_modification_or_replaceable":{"element_modification":{"name":{"name":"min"},"modification":{"symbol":"\u003d","expression":{"simple_expression":{"expression1":{"logical_term":{"logical_factor":{"relation":{"expression1":{"terms":[{"factor":{"primarys":[{"simple_primary":"0"}]}}]}}}}}}}},"comment":{}}}},{"element_modification_or_replaceable":{"element_modification":{"name":{"name":"max"},"modification":{"symbol":"\u003d","expression":{"simple_expression":{"expression1":{"logical_term":{"logical_factor":{"relation":{"expression1":{"terms":[{"factor":{"primarys":[{"simple_primary":"1"}]}}]}}}}}}}},"comment":{}}}}]}}}},"condition_attribute":{"iF":"if","expression":{"simple_expression":{"expression1":{"logical_term":{"logical_factor":{"relation":{"expression1":{"terms":[{"factor":{"primarys":[{"component_reference":{"component":"use_C_in"}}]}}]}}}}}}}},"comment":{"comment":{"string":"\"Input that sepecify variable C\""},"annotation":{"prefix":"annotation","annotation":{"argument_list":{"argument":[{"element_modification_or_replaceable":{"element_modification":{"name":{"name":"Placement"},"modification":{"class_modification":{"argument_list":{"argument":[{"element_modification_or_replaceable":{"element_modification":{"name":{"name":"transformation"},"modification":{"class_modification":{"argument_list":{"argument":[{"element_modification_or_replaceable":{"element_modification":{"name":{"name":"extent"},"modification":{"symbol":"\u003d","expression":{"simple_expression":{"expression1":{"logical_term":{"logical_factor":{"relation":{"expression1":{"terms":[{"factor":{"primarys":[{"function_arguments":{"argument":{"expressions":{"simple_expression":{"expression1":{"logical_term":{"logical_factor":{"relation":{"expression1":{"terms":[{"factor":{"primarys":[{"function_arguments":{"argument":{"expressions":{"simple_expression":{"expression1":{"logical_term":{"logical_factor":{"relation":{"expression1":{"add_pre":{"add_op":"-"},"terms":[{"factor":{"primarys":[{"simple_primary":"20"}]}}]}}}}}}}},"arguments":{"argument":{"expressions":{"simple_expression":{"expression1":{"logical_term":{"logical_factor":{"relation":{"expression1":{"add_pre":{"add_op":"-"},"terms":[{"factor":{"primarys":[{"simple_primary":"20"}]}}]}}}}}}}}}}}]}}]}}}}}}}},"arguments":{"argument":{"expressions":{"simple_expression":{"expression1":{"logical_term":{"logical_factor":{"relation":{"expression1":{"terms":[{"factor":{"primarys":[{"function_arguments":{"argument":{"expressions":{"simple_expression":{"expression1":{"logical_term":{"logical_factor":{"relation":{"expression1":{"terms":[{"factor":{"primarys":[{"simple_primary":"20"}]}}]}}}}}}}},"arguments":{"argument":{"expressions":{"simple_expression":{"expression1":{"logical_term":{"logical_factor":{"relation":{"expression1":{"terms":[{"factor":{"primarys":[{"simple_primary":"20"}]}}]}}}}}}}}}}}]}}]}}}}}}}}}}}]}}]}}}}}}}},"comment":{}}}},{"element_modification_or_replaceable":{"element_modification":{"name":{"name":"rotation"},"modification":{"symbol":"\u003d","expression":{"simple_expression":{"expression1":{"logical_term":{"logical_factor":{"relation":{"expression1":{"terms":[{"factor":{"primarys":[{"simple_primary":"270"}]}}]}}}}}}}},"comment":{}}}},{"element_modification_or_replaceable":{"element_modification":{"name":{"name":"origin"},"modification":{"symbol":"\u003d","expression":{"simple_expression":{"expression1":{"logical_term":{"logical_factor":{"relation":{"expression1":{"terms":[{"factor":{"primarys":[{"function_arguments":{"argument":{"expressions":{"simple_expression":{"expression1":{"logical_term":{"logical_factor":{"relation":{"expression1":{"terms":[{"factor":{"primarys":[{"simple_primary":"0"}]}}]}}}}}}}},"arguments":{"argument":{"expressions":{"simple_expression":{"expression1":{"logical_term":{"logical_factor":{"relation":{"expression1":{"terms":[{"factor":{"primarys":[{"simple_primary":"100"}]}}]}}}}}}}}}}}]}}]}}}}}}}},"comment":{}}}}]}}},"comment":{}}}}]}}},"comment":{}}}}]}}}}}]}}},{"component_clause":{"type_prefix":{},"type_specifier":{"specifier":{"name":"Modelica.Blocks.Interfaces.RealInput"}},"component_list":{"component_declaration":[{"declaration":{"name":"y_L","modification":{"class_modification":{"argument_list":{"argument":[{"element_modification_or_replaceable":{"element_modification":{"name":{"name":"min"},"modification":{"symbol":"\u003d","expression":{"simple_expression":{"expression1":{"logical_term":{"logical_factor":{"relation":{"expression1":{"terms":[{"factor":{"primarys":[{"simple_primary":"0"}]}}]}}}}}}}},"comment":{}}}},{"element_modification_or_replaceable":{"element_modification":{"name":{"name":"max"},"modification":{"symbol":"\u003d","expression":{"simple_expression":{"expression1":{"logical_term":{"logical_factor":{"relation":{"expression1":{"terms":[{"factor":{"primarys":[{"simple_primary":"1"}]}}]}}}}}}}},"comment":{}}}}]}}}},"condition_attribute":{"iF":"if","expression":{"simple_expression":{"expression1":{"logical_term":{"logical_factor":{"relation":{"expression1":{"terms":[{"factor":{"primarys":[{"component_reference":{"component":"use_L_in"}}]}}]}}}}}}}},"comment":{"comment":{"string":"\"Input that sepecify variable L\""},"annotation":{"prefix":"annotation","annotation":{"argument_list":{"argument":[{"element_modification_or_replaceable":{"element_modification":{"name":{"name":"Placement"},"modification":{"class_modification":{"argument_list":{"argument":[{"element_modification_or_replaceable":{"element_modification":{"name":{"name":"transformation"},"modification":{"class_modification":{"argument_list":{"argument":[{"element_modification_or_replaceable":{"element_modification":{"name":{"name":"extent"},"modification":{"symbol":"\u003d","expression":{"simple_expression":{"expression1":{"logical_term":{"logical_factor":{"relation":{"expression1":{"terms":[{"factor":{"primarys":[{"function_arguments":{"argument":{"expressions":{"simple_expression":{"expression1":{"logical_term":{"logical_factor":{"relation":{"expression1":{"terms":[{"factor":{"primarys":[{"function_arguments":{"argument":{"expressions":{"simple_expression":{"expression1":{"logical_term":{"logical_factor":{"relation":{"expression1":{"add_pre":{"add_op":"-"},"terms":[{"factor":{"primarys":[{"simple_primary":"20"}]}}]}}}}}}}},"arguments":{"argument":{"expressions":{"simple_expression":{"expression1":{"logical_term":{"logical_factor":{"relation":{"expression1":{"add_pre":{"add_op":"-"},"terms":[{"factor":{"primarys":[{"simple_primary":"20"}]}}]}}}}}}}}}}}]}}]}}}}}}}},"arguments":{"argument":{"expressions":{"simple_expression":{"expression1":{"logical_term":{"logical_factor":{"relation":{"expression1":{"terms":[{"factor":{"primarys":[{"function_arguments":{"argument":{"expressions":{"simple_expression":{"expression1":{"logical_term":{"logical_factor":{"relation":{"expression1":{"terms":[{"factor":{"primarys":[{"simple_primary":"20"}]}}]}}}}}}}},"arguments":{"argument":{"expressions":{"simple_expression":{"expression1":{"logical_term":{"logical_factor":{"relation":{"expression1":{"terms":[{"factor":{"primarys":[{"simple_primary":"20"}]}}]}}}}}}}}}}}]}}]}}}}}}}}}}}]}}]}}}}}}}},"comment":{}}}},{"element_modification_or_replaceable":{"element_modification":{"name":{"name":"rotation"},"modification":{"symbol":"\u003d","expression":{"simple_expression":{"expression1":{"logical_term":{"logical_factor":{"relation":{"expression1":{"terms":[{"factor":{"primarys":[{"simple_primary":"270"}]}}]}}}}}}}},"comment":{}}}},{"element_modification_or_replaceable":{"element_modification":{"name":{"name":"origin"},"modification":{"symbol":"\u003d","expression":{"simple_expression":{"expression1":{"logical_term":{"logical_factor":{"relation":{"expression1":{"terms":[{"factor":{"primarys":[{"function_arguments":{"argument":{"expressions":{"simple_expression":{"expression1":{"logical_term":{"logical_factor":{"relation":{"expression1":{"terms":[{"factor":{"primarys":[{"simple_primary":"40"}]}}]}}}}}}}},"arguments":{"argument":{"expressions":{"simple_expression":{"expression1":{"logical_term":{"logical_factor":{"relation":{"expression1":{"terms":[{"factor":{"primarys":[{"simple_primary":"100"}]}}]}}}}}}}}}}}]}}]}}}}}}}},"comment":{}}}}]}}},"comment":{}}}}]}}},"comment":{}}}}]}}}}}]}}}]},"prefixed_element":[{"element":[{"component_clause":{"type_prefix":{},"type_specifier":{"specifier":{"name":"Modelica.Blocks.Interfaces.RealOutput"}},"component_list":{"component_declaration":[{"declaration":{"name":"y_R_internal"},"comment":{"comment":{"string":"\"Internal signal used to compute the variable R_internal\""}}}]}}},{"component_clause":{"type_prefix":{},"type_specifier":{"specifier":{"name":"Modelica.Blocks.Interfaces.RealOutput"}},"component_list":{"component_declaration":[{"declaration":{"name":"y_C_internal"},"comment":{"comment":{"string":"\"Internal signal used to compute the variable C_internal\""}}}]}}},{"component_clause":{"type_prefix":{},"type_specifier":{"specifier":{"name":"Modelica.Blocks.Interfaces.RealOutput"}},"component_list":{"component_declaration":[{"declaration":{"name":"y_L_internal"},"comment":{"comment":{"string":"\"Internal signal used to compute the variable L_internal\""}}}]}}},{"component_clause":{"type_prefix":{},"type_specifier":{"specifier":{"name":"Modelica.SIunits.Resistance"}},"component_list":{"component_declaration":[{"declaration":{"name":"R_internal"},"comment":{"comment":{"string":"\"Actual resistance used to compute the impedance\""}}}]}}},{"component_clause":{"type_prefix":{},"type_specifier":{"specifier":{"name":"Modelica.SIunits.Inductance"}},"component_list":{"component_declaration":[{"declaration":{"name":"L_internal"},"comment":{"comment":{"string":"\"Actual inductance used to compute the impedance\""}}}]}}},{"component_clause":{"type_prefix":{},"type_specifier":{"specifier":{"name":"Modelica.SIunits.Capacitance"}},"component_list":{"component_declaration":[{"declaration":{"name":"C_internal"},"comment":{"comment":{"string":"\"Actual capacitance used to compute the impedance\""}}}]}}}]}],"equation_section":[{"prefix":" equation","equation":[{"name":{"name":"assert"},"function_call_args":{"arguments":{"argument":{"expressions":{"simple_expression":{"expression1":{"logical_term":{"logical_factor":{"relation":{"expression1":{"terms":[{"factor":{"primarys":[{"output_expression_list":{"expression":[{"simple_expression":{"expression1":{"logical_term":{"logical_factor":{"not":"not","relation":{"expression1":{"terms":[{"factor":{"primarys":[{"component_reference":{"component":"use_R_in"}}]}}]}}}}}}}]}}]}}]}}}},"logical_relation":"or","logical_terms":[{"logical_factor":{"relation":{"expression1":{"terms":[{"factor":{"primarys":[{"component_reference":{"component":"RMin"}}]}}]},"rel_op":{"rel_op":"\u003c"},"expression2":{"terms":[{"factor":{"primarys":[{"component_reference":{"component":"RMax"}}]}}]}}}}]}}}},"arguments":{"argument":{"expressions":{"simple_expression":{"expression1":{"logical_term":{"logical_factor":{"relation":{"expression1":{"terms":[{"factor":{"primarys":[{"simple_primary":"\"The value of RMin has to be lower than RMax\""}]}}]}}}}}}}}}}},"comment":{"comment":{}}},{"name":{"name":"assert"},"function_call_args":{"arguments":{"argument":{"expressions":{"simple_expression":{"expression1":{"logical_term":{"logical_factor":{"relation":{"expression1":{"terms":[{"factor":{"primarys":[{"output_expression_list":{"expression":[{"simple_expression":{"expression1":{"logical_term":{"logical_factor":{"not":"not","relation":{"expression1":{"terms":[{"factor":{"primarys":[{"component_reference":{"component":"use_L_in"}}]}}]}}}}}}}]}}]}}]}}}},"logical_relation":"or","logical_terms":[{"logical_factor":{"relation":{"expression1":{"terms":[{"factor":{"primarys":[{"component_reference":{"component":"LMin"}}]}}]},"rel_op":{"rel_op":"\u003c"},"expression2":{"terms":[{"factor":{"primarys":[{"component_reference":{"component":"LMax"}}]}}]}}}}]}}}},"arguments":{"argument":{"expressions":{"simple_expression":{"expression1":{"logical_term":{"logical_factor":{"relation":{"expression1":{"terms":[{"factor":{"primarys":[{"simple_primary":"\"The value of Lmin has to be lower than Lmax\""}]}}]}}}}}}}}}}},"comment":{"comment":{}}},{"name":{"name":"assert"},"function_call_args":{"arguments":{"argument":{"expressions":{"simple_expression":{"expression1":{"logical_term":{"logical_factor":{"relation":{"expression1":{"terms":[{"factor":{"primarys":[{"output_expression_list":{"expression":[{"simple_expression":{"expression1":{"logical_term":{"logical_factor":{"not":"not","relation":{"expression1":{"terms":[{"factor":{"primarys":[{"component_reference":{"component":"use_C_in"}}]}}]}}}}}}}]}}]}}]}}}},"logical_relation":"or","logical_terms":[{"logical_factor":{"relation":{"expression1":{"terms":[{"factor":{"primarys":[{"component_reference":{"component":"CMin"}}]}}]},"rel_op":{"rel_op":"\u003c"},"expression2":{"terms":[{"factor":{"primarys":[{"component_reference":{"component":"CMax"}}]}}]}}}}]}}}},"arguments":{"argument":{"expressions":{"simple_expression":{"expression1":{"logical_term":{"logical_factor":{"relation":{"expression1":{"terms":[{"factor":{"primarys":[{"simple_primary":"\"The value of Cmin has to be lower than Cmax\""}]}}]}}}}}}}}}}},"comment":{"comment":{}}},{"connect_clause":{"component":[{"component":"y_R"},{"component":"y_R_internal"}]},"comment":{"comment":{}}},{"connect_clause":{"component":[{"component":"y_C"},{"component":"y_C_internal"}]},"comment":{"comment":{}}},{"connect_clause":{"component":[{"component":"y_L"},{"component":"y_L_internal"}]},"comment":{"comment":{}}},{"if_equation":{"iF":{"simple_expression":{"expression1":{"logical_term":{"logical_factor":{"not":"not","relation":{"expression1":{"terms":[{"factor":{"primarys":[{"component_reference":{"component":"use_R_in"}}]}}]}}}}}}},"if_then":[{"simple_expression":{"expression1":{"logical_term":{"logical_factor":{"relation":{"expression1":{"terms":[{"factor":{"primarys":[{"component_reference":{"component":"y_R_internal"}}]}}]}}}}}},"operator":"\u003d","expression":{"simple_expression":{"expression1":{"logical_term":{"logical_factor":{"relation":{"expression1":{"terms":[{"factor":{"primarys":[{"simple_primary":"0"}]}}]}}}}}}},"comment":{"comment":{}}}]},"comment":{"comment":{}}},{"if_equation":{"iF":{"simple_expression":{"expression1":{"logical_term":{"logical_factor":{"not":"not","relation":{"expression1":{"terms":[{"factor":{"primarys":[{"component_reference":{"component":"use_C_in"}}]}}]}}}}}}},"if_then":[{"simple_expression":{"expression1":{"logical_term":{"logical_factor":{"relation":{"expression1":{"terms":[{"factor":{"primarys":[{"component_reference":{"component":"y_C_internal"}}]}}]}}}}}},"operator":"\u003d","expression":{"simple_expression":{"expression1":{"logical_term":{"logical_factor":{"relation":{"expression1":{"terms":[{"factor":{"primarys":[{"simple_primary":"0"}]}}]}}}}}}},"comment":{"comment":{}}}]},"comment":{"comment":{}}},{"if_equation":{"iF":{"simple_expression":{"expression1":{"logical_term":{"logical_factor":{"not":"not","relation":{"expression1":{"terms":[{"factor":{"primarys":[{"component_reference":{"component":"use_L_in"}}]}}]}}}}}}},"if_then":[{"simple_expression":{"expression1":{"logical_term":{"logical_factor":{"relation":{"expression1":{"terms":[{"factor":{"primarys":[{"component_reference":{"component":"y_L_internal"}}]}}]}}}}}},"operator":"\u003d","expression":{"simple_expression":{"expression1":{"logical_term":{"logical_factor":{"relation":{"expression1":{"terms":[{"factor":{"primarys":[{"simple_primary":"0"}]}}]}}}}}}},"comment":{"comment":{}}}]},"comment":{"comment":{}}},{"if_equation":{"iF":{"simple_expression":{"expression1":{"logical_term":{"logical_factor":{"not":"not","relation":{"expression1":{"terms":[{"factor":{"primarys":[{"component_reference":{"component":"use_R_in"}}]}}]}}}}}}},"if_then":[{"simple_expression":{"expression1":{"logical_term":{"logical_factor":{"relation":{"expression1":{"terms":[{"factor":{"primarys":[{"component_reference":{"component":"R_internal"}}]}}]}}}}}},"operator":"\u003d","expression":{"simple_expression":{"expression1":{"logical_term":{"logical_factor":{"relation":{"expression1":{"terms":[{"factor":{"primarys":[{"component_reference":{"component":"R"}}]}}]}}}}}}},"comment":{"comment":{}}},{"simple_expression":{"expression1":{"logical_term":{"logical_factor":{"relation":{"expression1":{"terms":[{"factor":{"primarys":[{"component_reference":{"component":"R_internal"}}]}}]}}}}}},"operator":"\u003d","expression":{"simple_expression":{"expression1":{"logical_term":{"logical_factor":{"relation":{"expression1":{"terms":[{"factor":{"primarys":[{"component_reference":{"component":"RMin"}}]}},{"factor":{"primarys":[{"component_reference":{"component":"y_R_internal"}}]},"mul_op":[{"mul_op":"*"}],"factors":[{"primarys":[{"output_expression_list":{"expression":[{"simple_expression":{"expression1":{"logical_term":{"logical_factor":{"relation":{"expression1":{"terms":[{"factor":{"primarys":[{"component_reference":{"component":"RMax"}}]}},{"factor":{"primarys":[{"component_reference":{"component":"RMin"}}]}}],"adds":[{"add_op":"-"}]}}}}}}}]}}]}]}],"adds":[{"add_op":"+"}]}}}}}}},"comment":{"comment":{}}}]},"comment":{"comment":{}}},{"if_equation":{"iF":{"simple_expression":{"expression1":{"logical_term":{"logical_factor":{"not":"not","relation":{"expression1":{"terms":[{"factor":{"primarys":[{"component_reference":{"component":"use_C_in"}}]}}]}}}}}}},"if_then":[{"simple_expression":{"expression1":{"logical_term":{"logical_factor":{"relation":{"expression1":{"terms":[{"factor":{"primarys":[{"component_reference":{"component":"C_internal"}}]}}]}}}}}},"operator":"\u003d","expression":{"simple_expression":{"expression1":{"logical_term":{"logical_factor":{"relation":{"expression1":{"terms":[{"factor":{"primarys":[{"component_reference":{"component":"C"}}]}}]}}}}}}},"comment":{"comment":{}}},{"simple_expression":{"expression1":{"logical_term":{"logical_factor":{"relation":{"expression1":{"terms":[{"factor":{"primarys":[{"component_reference":{"component":"C_internal"}}]}}]}}}}}},"operator":"\u003d","expression":{"simple_expression":{"expression1":{"logical_term":{"logical_factor":{"relation":{"expression1":{"terms":[{"factor":{"primarys":[{"component_reference":{"component":"CMin"}}]}},{"factor":{"primarys":[{"component_reference":{"component":"y_C_internal"}}]},"mul_op":[{"mul_op":"*"}],"factors":[{"primarys":[{"output_expression_list":{"expression":[{"simple_expression":{"expression1":{"logical_term":{"logical_factor":{"relation":{"expression1":{"terms":[{"factor":{"primarys":[{"component_reference":{"component":"CMax"}}]}},{"factor":{"primarys":[{"component_reference":{"component":"CMin"}}]}}],"adds":[{"add_op":"-"}]}}}}}}}]}}]}]}],"adds":[{"add_op":"+"}]}}}}}}},"comment":{"comment":{}}}]},"comment":{"comment":{}}},{"if_equation":{"iF":{"simple_expression":{"expression1":{"logical_term":{"logical_factor":{"not":"not","relation":{"expression1":{"terms":[{"factor":{"primarys":[{"component_reference":{"component":"use_L_in"}}]}}]}}}}}}},"if_then":[{"simple_expression":{"expression1":{"logical_term":{"logical_factor":{"relation":{"expression1":{"terms":[{"factor":{"primarys":[{"component_reference":{"component":"L_internal"}}]}}]}}}}}},"operator":"\u003d","expression":{"simple_expression":{"expression1":{"logical_term":{"logical_factor":{"relation":{"expression1":{"terms":[{"factor":{"primarys":[{"component_reference":{"component":"L"}}]}}]}}}}}}},"comment":{"comment":{}}},{"simple_expression":{"expression1":{"logical_term":{"logical_factor":{"relation":{"expression1":{"terms":[{"factor":{"primarys":[{"component_reference":{"component":"L_internal"}}]}}]}}}}}},"operator":"\u003d","expression":{"simple_expression":{"expression1":{"logical_term":{"logical_factor":{"relation":{"expression1":{"terms":[{"factor":{"primarys":[{"component_reference":{"component":"LMin"}}]}},{"factor":{"primarys":[{"component_reference":{"component":"y_L_internal"}}]},"mul_op":[{"mul_op":"*"}],"factors":[{"primarys":[{"output_expression_list":{"expression":[{"simple_expression":{"expression1":{"logical_term":{"logical_factor":{"relation":{"expression1":{"terms":[{"factor":{"primarys":[{"component_reference":{"component":"LMax"}}]}},{"factor":{"primarys":[{"component_reference":{"component":"LMin"}}]}}],"adds":[{"add_op":"-"}]}}}}}}}]}}]}]}],"adds":[{"add_op":"+"}]}}}}}}},"comment":{"comment":{}}}]},"comment":{"comment":{}}}]}],"comp_annotation":{"prefix":"annotation","annotation":{"argument_list":{"argument":[{"element_modification_or_replaceable":{"element_modification":{"name":{"name":"Documentation"},"modification":{"class_modification":{"argument_list":{"argument":[{"element_modification_or_replaceable":{"element_modification":{"name":{"name":"info"},"modification":{"symbol":"\u003d","expression":{"simple_expression":{"expression1":{"logical_term":{"logical_factor":{"relation":{"expression1":{"terms":[{"factor":{"primarys":[{"simple_primary":"\"\u003chtml\u003e\n\u003cp\u003e\nThis model represents a generalized interface for an impedance.\n\u003c/p\u003e\n\u003cp\u003e\nThe model has a single generalized electric terminal of type\n\u003ca href\u003d\\\"modelica://Buildings.Electrical.Interfaces.Terminal\\\"\u003e\nBuildings.Electrical.Interfaces.Terminal\u003c/a\u003e\nthat can be redeclared.\nThe impedance can be of different types:\n\u003c/p\u003e\n\u003col\u003e\n\u003cli\u003eresistive,\u003c/li\u003e\n\u003cli\u003einductive,\u003c/li\u003e\n\u003cli\u003eresistive and inductive,\u003c/li\u003e\n\u003cli\u003ecapacitive, and\u003c/li\u003e\n\u003cli\u003eresistive and capacitive.\u003c/li\u003e\n\u003c/ol\u003e\n\u003cp\u003e\nThe values of the resistance \u003ccode\u003eR\u003c/code\u003e, capacitance \u003ccode\u003eC\u003c/code\u003e and\ninductance \u003ccode\u003eL\u003c/code\u003e can be\nspecified as parameters of the model.\n\u003c/p\u003e\n\u003cp\u003e\nThe values of the resistance \u003ccode\u003eR\u003c/code\u003e, capacitance \u003ccode\u003eC\u003c/code\u003e\nand inductance \u003ccode\u003eL\u003c/code\u003e can also be\nspecified by using the input variables \u003ccode\u003ey_R\u003c/code\u003e, \u003ccode\u003ey_C\u003c/code\u003e,\nand \u003ccode\u003ey_L\u003c/code\u003e that are Real values between \u003ci\u003e[0,1]\u003c/i\u003e.\u003cbr/\u003e\nThese input values are enabled by the boolean flags \u003ccode\u003euse_R_in\u003c/code\u003e,\n\u003ccode\u003euse_L_in\u003c/code\u003e, and\n\u003ccode\u003euse_C_in\u003c/code\u003e.\n\u003c/p\u003e\n\u003ch5\u003eExample\u003c/h5\u003e\n\u003cp\u003e\nIf the flag \u003ccode\u003euse_R_in \u003d true\u003c/code\u003e, the value of \u003ccode\u003eR\u003c/code\u003e is computed as\n\u003c/p\u003e\n\u003cp align\u003d\\\"center\\\" style\u003d\\\"font-style:italic;\\\"\u003e\nR \u003d R\u003csub\u003emin\u003c/sub\u003e + y\u003csub\u003eR\u003c/sub\u003e (R\u003csub\u003emax\u003c/sub\u003e - R\u003csub\u003emin\u003c/sub\u003e)\n\u003c/p\u003e\n\u003c/html\u003e\""}]}}]}}}}}}}},"comment":{}}}},{"element_modification_or_replaceable":{"element_modification":{"name":{"name":"revisions"},"modification":{"symbol":"\u003d","expression":{"simple_expression":{"expression1":{"logical_term":{"logical_factor":{"relation":{"expression1":{"terms":[{"factor":{"primarys":[{"simple_primary":"\"\u003chtml\u003e\n\u003cul\u003e\n\u003cli\u003e\nMay 15, 2014, by Marco Bonvini:\u003cbr/\u003e\nCreated documentation.\n\u003c/li\u003e\n\u003c/ul\u003e\n\u003c/html\u003e\""}]}}]}}}}}}}},"comment":{}}}}]}}},"comment":{}}}}]}}}}}}}]}