{"within":[{"name":"Buildings.Applications.DataCenters.ChillerCooled.Equipment.BaseClasses"}],"class_definition":[{"class_prefixes":{"prefix":"partial model"},"class_specifier":{"long_class_specifier":{"name":"SignalFilter","comment":{"string":"\"Partial model that implements the filtered opening for valves and dampers\""},"composition":{"protect":["protected"],"element_list":{"element":[{"extends_clause":{"name":{"name":"Buildings.Applications.DataCenters.ChillerCooled.Equipment.BaseClasses.SignalFilterParameters"}}}]},"prefixed_element":[{"element":[{"component_clause":{"type_prefix":{},"type_specifier":{"specifier":{"name":"Modelica.Blocks.Interfaces.RealOutput"}},"array_subscripts":{"subscript":[{"subscript":{"simple_expression":{"expression1":{"logical_term":{"logical_factor":{"relation":{"expression1":{"terms":[{"factor":{"primarys":[{"component_reference":{"component":"numFil"}}]}}]}}}}}}}}]},"component_list":{"component_declaration":[{"declaration":{"name":"y_actual"},"comment":{"comment":{"string":"\"Actual valve position\""},"annotation":{"prefix":"annotation","annotation":{"argument_list":{"argument":[{"element_modification_or_replaceable":{"element_modification":{"name":{"name":"Placement"},"modification":{"class_modification":{"argument_list":{"argument":[{"element_modification_or_replaceable":{"element_modification":{"name":{"name":"transformation"},"modification":{"class_modification":{"argument_list":{"argument":[{"element_modification_or_replaceable":{"element_modification":{"name":{"name":"extent"},"modification":{"symbol":"\u003d","expression":{"simple_expression":{"expression1":{"logical_term":{"logical_factor":{"relation":{"expression1":{"terms":[{"factor":{"primarys":[{"function_arguments":{"argument":{"expressions":{"simple_expression":{"expression1":{"logical_term":{"logical_factor":{"relation":{"expression1":{"terms":[{"factor":{"primarys":[{"function_arguments":{"argument":{"expressions":{"simple_expression":{"expression1":{"logical_term":{"logical_factor":{"relation":{"expression1":{"add_pre":{"add_op":"-"},"terms":[{"factor":{"primarys":[{"simple_primary":"28"}]}}]}}}}}}}},"arguments":{"argument":{"expressions":{"simple_expression":{"expression1":{"logical_term":{"logical_factor":{"relation":{"expression1":{"terms":[{"factor":{"primarys":[{"simple_primary":"66"}]}}]}}}}}}}}}}}]}}]}}}}}}}},"arguments":{"argument":{"expressions":{"simple_expression":{"expression1":{"logical_term":{"logical_factor":{"relation":{"expression1":{"terms":[{"factor":{"primarys":[{"function_arguments":{"argument":{"expressions":{"simple_expression":{"expression1":{"logical_term":{"logical_factor":{"relation":{"expression1":{"add_pre":{"add_op":"-"},"terms":[{"factor":{"primarys":[{"simple_primary":"12"}]}}]}}}}}}}},"arguments":{"argument":{"expressions":{"simple_expression":{"expression1":{"logical_term":{"logical_factor":{"relation":{"expression1":{"terms":[{"factor":{"primarys":[{"simple_primary":"82"}]}}]}}}}}}}}}}}]}}]}}}}}}}}}}}]}}]}}}}}}}},"comment":{}}}}]}}},"comment":{}}}}]}}},"comment":{}}}}]}}}}}]}}},{"component_clause":{"type_prefix":{},"type_specifier":{"specifier":{"name":"Modelica.Blocks.Continuous.Filter"}},"array_subscripts":{"subscript":[{"subscript":{"simple_expression":{"expression1":{"logical_term":{"logical_factor":{"relation":{"expression1":{"terms":[{"factor":{"primarys":[{"component_reference":{"component":"numFil"}}]}}]}}}}}}}}]},"component_list":{"component_declaration":[{"declaration":{"name":"filter","modification":{"class_modification":{"argument_list":{"argument":[{"element_modification_or_replaceable":{"prefix":"each ","element_modification":{"name":{"name":"order"},"modification":{"symbol":"\u003d","expression":{"simple_expression":{"expression1":{"logical_term":{"logical_factor":{"relation":{"expression1":{"terms":[{"factor":{"primarys":[{"simple_primary":"2"}]}}]}}}}}}}},"comment":{}}}},{"element_modification_or_replaceable":{"prefix":"each ","element_modification":{"name":{"name":"f_cut"},"modification":{"symbol":"\u003d","expression":{"simple_expression":{"expression1":{"logical_term":{"logical_factor":{"relation":{"expression1":{"terms":[{"factor":{"primarys":[{"simple_primary":"5"}]},"mul_op":[{"mul_op":"/"}],"factors":[{"primarys":[{"output_expression_list":{"expression":[{"simple_expression":{"expression1":{"logical_term":{"logical_factor":{"relation":{"expression1":{"terms":[{"factor":{"primarys":[{"simple_primary":"2"}]},"mul_op":[{"mul_op":"*"},{"mul_op":"*"}],"factors":[{"primarys":[{"component_reference":{"component":"Modelica.Constants.pi"}}]},{"primarys":[{"component_reference":{"component":"riseTimeValve"}}]}]}]}}}}}}}]}}]}]}]}}}}}}}},"comment":{}}}},{"element_modification_or_replaceable":{"prefix":"each final","element_modification":{"name":{"name":"init"},"modification":{"symbol":"\u003d","expression":{"simple_expression":{"expression1":{"logical_term":{"logical_factor":{"relation":{"expression1":{"terms":[{"factor":{"primarys":[{"component_reference":{"component":"initValve"}}]}}]}}}}}}}},"comment":{}}}},{"element_modification_or_replaceable":{"prefix":"final","element_modification":{"name":{"name":"y_start"},"modification":{"symbol":"\u003d","expression":{"simple_expression":{"expression1":{"logical_term":{"logical_factor":{"relation":{"expression1":{"terms":[{"factor":{"primarys":[{"component_reference":{"component":"yValve_start"}}]}}]}}}}}}}},"comment":{}}}},{"element_modification_or_replaceable":{"prefix":"each final","element_modification":{"name":{"name":"analogFilter"},"modification":{"symbol":"\u003d","expression":{"simple_expression":{"expression1":{"logical_term":{"logical_factor":{"relation":{"expression1":{"terms":[{"factor":{"primarys":[{"component_reference":{"component":"Modelica.Blocks.Types.AnalogFilter.CriticalDamping"}}]}}]}}}}}}}},"comment":{}}}},{"element_modification_or_replaceable":{"prefix":"each final","element_modification":{"name":{"name":"filterType"},"modification":{"symbol":"\u003d","expression":{"simple_expression":{"expression1":{"logical_term":{"logical_factor":{"relation":{"expression1":{"terms":[{"factor":{"primarys":[{"component_reference":{"component":"Modelica.Blocks.Types.FilterType.LowPass"}}]}}]}}}}}}}},"comment":{}}}},{"element_modification_or_replaceable":{"element_modification":{"name":{"name":"x"},"modification":{"class_modification":{"argument_list":{"argument":[{"element_modification_or_replaceable":{"prefix":"each ","element_modification":{"name":{"name":"stateSelect"},"modification":{"symbol":"\u003d","expression":{"simple_expression":{"expression1":{"logical_term":{"logical_factor":{"relation":{"expression1":{"terms":[{"factor":{"primarys":[{"component_reference":{"component":"StateSelect.always"}}]}}]}}}}}}}},"comment":{}}}}]}}},"comment":{}}}}]}}}},"condition_attribute":{"iF":"if","expression":{"simple_expression":{"expression1":{"logical_term":{"logical_factor":{"relation":{"expression1":{"terms":[{"factor":{"primarys":[{"component_reference":{"component":"use_inputFilter"}}]}}]}}}}}}}},"comment":{"comment":{"string":"\"Second order filters to approximate valve opening time, and to improve numerics\""},"annotation":{"prefix":"annotation","annotation":{"argument_list":{"argument":[{"element_modification_or_replaceable":{"element_modification":{"name":{"name":"Placement"},"modification":{"class_modification":{"argument_list":{"argument":[{"element_modification_or_replaceable":{"element_modification":{"name":{"name":"transformation"},"modification":{"class_modification":{"argument_list":{"argument":[{"element_modification_or_replaceable":{"element_modification":{"name":{"name":"extent"},"modification":{"symbol":"\u003d","expression":{"simple_expression":{"expression1":{"logical_term":{"logical_factor":{"relation":{"expression1":{"terms":[{"factor":{"primarys":[{"function_arguments":{"argument":{"expressions":{"simple_expression":{"expression1":{"logical_term":{"logical_factor":{"relation":{"expression1":{"terms":[{"factor":{"primarys":[{"function_arguments":{"argument":{"expressions":{"simple_expression":{"expression1":{"logical_term":{"logical_factor":{"relation":{"expression1":{"add_pre":{"add_op":"-"},"terms":[{"factor":{"primarys":[{"simple_primary":"54"}]}}]}}}}}}}},"arguments":{"argument":{"expressions":{"simple_expression":{"expression1":{"logical_term":{"logical_factor":{"relation":{"expression1":{"terms":[{"factor":{"primarys":[{"simple_primary":"78"}]}}]}}}}}}}}}}}]}}]}}}}}}}},"arguments":{"argument":{"expressions":{"simple_expression":{"expression1":{"logical_term":{"logical_factor":{"relation":{"expression1":{"terms":[{"factor":{"primarys":[{"function_arguments":{"argument":{"expressions":{"simple_expression":{"expression1":{"logical_term":{"logical_factor":{"relation":{"expression1":{"add_pre":{"add_op":"-"},"terms":[{"factor":{"primarys":[{"simple_primary":"42"}]}}]}}}}}}}},"arguments":{"argument":{"expressions":{"simple_expression":{"expression1":{"logical_term":{"logical_factor":{"relation":{"expression1":{"terms":[{"factor":{"primarys":[{"simple_primary":"90"}]}}]}}}}}}}}}}}]}}]}}}}}}}}}}}]}}]}}}}}}}},"comment":{}}}}]}}},"comment":{}}}}]}}},"comment":{}}}}]}}}}}]}}},{"component_clause":{"type_prefix":{},"type_specifier":{"specifier":{"name":"Modelica.Blocks.Interfaces.RealOutput"}},"array_subscripts":{"subscript":[{"subscript":{"simple_expression":{"expression1":{"logical_term":{"logical_factor":{"relation":{"expression1":{"terms":[{"factor":{"primarys":[{"component_reference":{"component":"numFil"}}]}}]}}}}}}}}]},"component_list":{"component_declaration":[{"declaration":{"name":"y_filtered"},"condition_attribute":{"iF":"if","expression":{"simple_expression":{"expression1":{"logical_term":{"logical_factor":{"relation":{"expression1":{"terms":[{"factor":{"primarys":[{"component_reference":{"component":"use_inputFilter"}}]}}]}}}}}}}},"comment":{"comment":{"string":"\"Filtered valve positions in the range 0..1\""},"annotation":{"prefix":"annotation","annotation":{"argument_list":{"argument":[{"element_modification_or_replaceable":{"element_modification":{"name":{"name":"Placement"},"modification":{"class_modification":{"argument_list":{"argument":[{"element_modification_or_replaceable":{"element_modification":{"name":{"name":"transformation"},"modification":{"class_modification":{"argument_list":{"argument":[{"element_modification_or_replaceable":{"element_modification":{"name":{"name":"extent"},"modification":{"symbol":"\u003d","expression":{"simple_expression":{"expression1":{"logical_term":{"logical_factor":{"relation":{"expression1":{"terms":[{"factor":{"primarys":[{"function_arguments":{"argument":{"expressions":{"simple_expression":{"expression1":{"logical_term":{"logical_factor":{"relation":{"expression1":{"terms":[{"factor":{"primarys":[{"function_arguments":{"argument":{"expressions":{"simple_expression":{"expression1":{"logical_term":{"logical_factor":{"relation":{"expression1":{"add_pre":{"add_op":"-"},"terms":[{"factor":{"primarys":[{"simple_primary":"28"}]}}]}}}}}}}},"arguments":{"argument":{"expressions":{"simple_expression":{"expression1":{"logical_term":{"logical_factor":{"relation":{"expression1":{"terms":[{"factor":{"primarys":[{"simple_primary":"76"}]}}]}}}}}}}}}}}]}}]}}}}}}}},"arguments":{"argument":{"expressions":{"simple_expression":{"expression1":{"logical_term":{"logical_factor":{"relation":{"expression1":{"terms":[{"factor":{"primarys":[{"function_arguments":{"argument":{"expressions":{"simple_expression":{"expression1":{"logical_term":{"logical_factor":{"relation":{"expression1":{"add_pre":{"add_op":"-"},"terms":[{"factor":{"primarys":[{"simple_primary":"12"}]}}]}}}}}}}},"arguments":{"argument":{"expressions":{"simple_expression":{"expression1":{"logical_term":{"logical_factor":{"relation":{"expression1":{"terms":[{"factor":{"primarys":[{"simple_primary":"92"}]}}]}}}}}}}}}}}]}}]}}}}}}}}}}}]}}]}}}}}}}},"comment":{}}}}]}}},"comment":{}}}},{"element_modification_or_replaceable":{"element_modification":{"name":{"name":"iconTransformation"},"modification":{"class_modification":{"argument_list":{"argument":[{"element_modification_or_replaceable":{"element_modification":{"name":{"name":"extent"},"modification":{"symbol":"\u003d","expression":{"simple_expression":{"expression1":{"logical_term":{"logical_factor":{"relation":{"expression1":{"terms":[{"factor":{"primarys":[{"function_arguments":{"argument":{"expressions":{"simple_expression":{"expression1":{"logical_term":{"logical_factor":{"relation":{"expression1":{"terms":[{"factor":{"primarys":[{"function_arguments":{"argument":{"expressions":{"simple_expression":{"expression1":{"logical_term":{"logical_factor":{"relation":{"expression1":{"terms":[{"factor":{"primarys":[{"simple_primary":"60"}]}}]}}}}}}}},"arguments":{"argument":{"expressions":{"simple_expression":{"expression1":{"logical_term":{"logical_factor":{"relation":{"expression1":{"terms":[{"factor":{"primarys":[{"simple_primary":"50"}]}}]}}}}}}}}}}}]}}]}}}}}}}},"arguments":{"argument":{"expressions":{"simple_expression":{"expression1":{"logical_term":{"logical_factor":{"relation":{"expression1":{"terms":[{"factor":{"primarys":[{"function_arguments":{"argument":{"expressions":{"simple_expression":{"expression1":{"logical_term":{"logical_factor":{"relation":{"expression1":{"terms":[{"factor":{"primarys":[{"simple_primary":"80"}]}}]}}}}}}}},"arguments":{"argument":{"expressions":{"simple_expression":{"expression1":{"logical_term":{"logical_factor":{"relation":{"expression1":{"terms":[{"factor":{"primarys":[{"simple_primary":"70"}]}}]}}}}}}}}}}}]}}]}}}}}}}}}}}]}}]}}}}}}}},"comment":{}}}}]}}},"comment":{}}}}]}}},"comment":{}}}}]}}}}}]}}}]}],"equation_section":[{"prefix":" equation","equation":[{"connect_clause":{"component":[{"component":"filter.y"},{"component":"y_filtered"}]},"comment":{"comment":{},"annotation":{"prefix":"annotation","annotation":{"argument_list":{"argument":[{"element_modification_or_replaceable":{"element_modification":{"name":{"name":"Line"},"modification":{"class_modification":{"argument_list":{"argument":[{"element_modification_or_replaceable":{"element_modification":{"name":{"name":"points"},"modification":{"symbol":"\u003d","expression":{"simple_expression":{"expression1":{"logical_term":{"logical_factor":{"relation":{"expression1":{"terms":[{"factor":{"primarys":[{"function_arguments":{"argument":{"expressions":{"simple_expression":{"expression1":{"logical_term":{"logical_factor":{"relation":{"expression1":{"terms":[{"factor":{"primarys":[{"function_arguments":{"argument":{"expressions":{"simple_expression":{"expression1":{"logical_term":{"logical_factor":{"relation":{"expression1":{"add_pre":{"add_op":"-"},"terms":[{"factor":{"primarys":[{"simple_primary":"41.4"}]}}]}}}}}}}},"arguments":{"argument":{"expressions":{"simple_expression":{"expression1":{"logical_term":{"logical_factor":{"relation":{"expression1":{"terms":[{"factor":{"primarys":[{"simple_primary":"84"}]}}]}}}}}}}}}}}]}}]}}}}}}}},"arguments":{"argument":{"expressions":{"simple_expression":{"expression1":{"logical_term":{"logical_factor":{"relation":{"expression1":{"terms":[{"factor":{"primarys":[{"function_arguments":{"argument":{"expressions":{"simple_expression":{"expression1":{"logical_term":{"logical_factor":{"relation":{"expression1":{"add_pre":{"add_op":"-"},"terms":[{"factor":{"primarys":[{"simple_primary":"32"}]}}]}}}}}}}},"arguments":{"argument":{"expressions":{"simple_expression":{"expression1":{"logical_term":{"logical_factor":{"relation":{"expression1":{"terms":[{"factor":{"primarys":[{"simple_primary":"84"}]}}]}}}}}}}}}}}]}}]}}}}}}}},"arguments":{"argument":{"expressions":{"simple_expression":{"expression1":{"logical_term":{"logical_factor":{"relation":{"expression1":{"terms":[{"factor":{"primarys":[{"function_arguments":{"argument":{"expressions":{"simple_expression":{"expression1":{"logical_term":{"logical_factor":{"relation":{"expression1":{"add_pre":{"add_op":"-"},"terms":[{"factor":{"primarys":[{"simple_primary":"20"}]}}]}}}}}}}},"arguments":{"argument":{"expressions":{"simple_expression":{"expression1":{"logical_term":{"logical_factor":{"relation":{"expression1":{"terms":[{"factor":{"primarys":[{"simple_primary":"84"}]}}]}}}}}}}}}}}]}}]}}}}}}}}}}}}]}}]}}}}}}}},"comment":{}}}},{"element_modification_or_replaceable":{"element_modification":{"name":{"name":"color"},"modification":{"symbol":"\u003d","expression":{"simple_expression":{"expression1":{"logical_term":{"logical_factor":{"relation":{"expression1":{"terms":[{"factor":{"primarys":[{"function_arguments":{"argument":{"expressions":{"simple_expression":{"expression1":{"logical_term":{"logical_factor":{"relation":{"expression1":{"terms":[{"factor":{"primarys":[{"simple_primary":"0"}]}}]}}}}}}}},"arguments":{"argument":{"expressions":{"simple_expression":{"expression1":{"logical_term":{"logical_factor":{"relation":{"expression1":{"terms":[{"factor":{"primarys":[{"simple_primary":"0"}]}}]}}}}}}}},"arguments":{"argument":{"expressions":{"simple_expression":{"expression1":{"logical_term":{"logical_factor":{"relation":{"expression1":{"terms":[{"factor":{"primarys":[{"simple_primary":"127"}]}}]}}}}}}}}}}}}]}}]}}}}}}}},"comment":{}}}}]}}},"comment":{}}}}]}}}}},{"if_equation":{"iF":{"simple_expression":{"expression1":{"logical_term":{"logical_factor":{"relation":{"expression1":{"terms":[{"factor":{"primarys":[{"component_reference":{"component":"use_inputFilter"}}]}}]}}}}}}},"if_then":[{"connect_clause":{"component":[{"component":"filter.y"},{"component":"y_actual"}]},"comment":{"comment":{},"annotation":{"prefix":"annotation","annotation":{"argument_list":{"argument":[{"element_modification_or_replaceable":{"element_modification":{"name":{"name":"Line"},"modification":{"class_modification":{"argument_list":{"argument":[{"element_modification_or_replaceable":{"element_modification":{"name":{"name":"points"},"modification":{"symbol":"\u003d","expression":{"simple_expression":{"expression1":{"logical_term":{"logical_factor":{"relation":{"expression1":{"terms":[{"factor":{"primarys":[{"function_arguments":{"argument":{"expressions":{"simple_expression":{"expression1":{"logical_term":{"logical_factor":{"relation":{"expression1":{"terms":[{"factor":{"primarys":[{"function_arguments":{"argument":{"expressions":{"simple_expression":{"expression1":{"logical_term":{"logical_factor":{"relation":{"expression1":{"add_pre":{"add_op":"-"},"terms":[{"factor":{"primarys":[{"simple_primary":"41.4"}]}}]}}}}}}}},"arguments":{"argument":{"expressions":{"simple_expression":{"expression1":{"logical_term":{"logical_factor":{"relation":{"expression1":{"terms":[{"factor":{"primarys":[{"simple_primary":"84"}]}}]}}}}}}}}}}}]}}]}}}}}}}},"arguments":{"argument":{"expressions":{"simple_expression":{"expression1":{"logical_term":{"logical_factor":{"relation":{"expression1":{"terms":[{"factor":{"primarys":[{"function_arguments":{"argument":{"expressions":{"simple_expression":{"expression1":{"logical_term":{"logical_factor":{"relation":{"expression1":{"add_pre":{"add_op":"-"},"terms":[{"factor":{"primarys":[{"simple_primary":"32"}]}}]}}}}}}}},"arguments":{"argument":{"expressions":{"simple_expression":{"expression1":{"logical_term":{"logical_factor":{"relation":{"expression1":{"terms":[{"factor":{"primarys":[{"simple_primary":"84"}]}}]}}}}}}}}}}}]}}]}}}}}}}},"arguments":{"argument":{"expressions":{"simple_expression":{"expression1":{"logical_term":{"logical_factor":{"relation":{"expression1":{"terms":[{"factor":{"primarys":[{"function_arguments":{"argument":{"expressions":{"simple_expression":{"expression1":{"logical_term":{"logical_factor":{"relation":{"expression1":{"add_pre":{"add_op":"-"},"terms":[{"factor":{"primarys":[{"simple_primary":"32"}]}}]}}}}}}}},"arguments":{"argument":{"expressions":{"simple_expression":{"expression1":{"logical_term":{"logical_factor":{"relation":{"expression1":{"terms":[{"factor":{"primarys":[{"simple_primary":"74"}]}}]}}}}}}}}}}}]}}]}}}}}}}},"arguments":{"argument":{"expressions":{"simple_expression":{"expression1":{"logical_term":{"logical_factor":{"relation":{"expression1":{"terms":[{"factor":{"primarys":[{"function_arguments":{"argument":{"expressions":{"simple_expression":{"expression1":{"logical_term":{"logical_factor":{"relation":{"expression1":{"add_pre":{"add_op":"-"},"terms":[{"factor":{"primarys":[{"simple_primary":"20"}]}}]}}}}}}}},"arguments":{"argument":{"expressions":{"simple_expression":{"expression1":{"logical_term":{"logical_factor":{"relation":{"expression1":{"terms":[{"factor":{"primarys":[{"simple_primary":"74"}]}}]}}}}}}}}}}}]}}]}}}}}}}}}}}}}]}}]}}}}}}}},"comment":{}}}},{"element_modification_or_replaceable":{"element_modification":{"name":{"name":"color"},"modification":{"symbol":"\u003d","expression":{"simple_expression":{"expression1":{"logical_term":{"logical_factor":{"relation":{"expression1":{"terms":[{"factor":{"primarys":[{"function_arguments":{"argument":{"expressions":{"simple_expression":{"expression1":{"logical_term":{"logical_factor":{"relation":{"expression1":{"terms":[{"factor":{"primarys":[{"simple_primary":"0"}]}}]}}}}}}}},"arguments":{"argument":{"expressions":{"simple_expression":{"expression1":{"logical_term":{"logical_factor":{"relation":{"expression1":{"terms":[{"factor":{"primarys":[{"simple_primary":"0"}]}}]}}}}}}}},"arguments":{"argument":{"expressions":{"simple_expression":{"expression1":{"logical_term":{"logical_factor":{"relation":{"expression1":{"terms":[{"factor":{"primarys":[{"simple_primary":"127"}]}}]}}}}}}}}}}}}]}}]}}}}}}}},"comment":{}}}}]}}},"comment":{}}}}]}}}}}]},"comment":{"comment":{}}}]}],"comp_annotation":{"prefix":"annotation","annotation":{"argument_list":{"argument":[{"element_modification_or_replaceable":{"element_modification":{"name":{"name":"Documentation"},"modification":{"class_modification":{"argument_list":{"argument":[{"element_modification_or_replaceable":{"element_modification":{"name":{"name":"revisions"},"modification":{"symbol":"\u003d","expression":{"simple_expression":{"expression1":{"logical_term":{"logical_factor":{"relation":{"expression1":{"terms":[{"factor":{"primarys":[{"simple_primary":"\"\u003chtml\u003e\n\u003cul\u003e\n\u003cli\u003e\nJune 30, 2017, by Yangyang Fu:\u003cbr/\u003e\nFirst implementation.\n\u003c/li\u003e\n\u003c/ul\u003e\n\u003c/html\u003e\""}]}}]}}}}}}}},"comment":{}}}},{"element_modification_or_replaceable":{"element_modification":{"name":{"name":"info"},"modification":{"symbol":"\u003d","expression":{"simple_expression":{"expression1":{"logical_term":{"logical_factor":{"relation":{"expression1":{"terms":[{"factor":{"primarys":[{"simple_primary":"\"\u003chtml\u003e\n\u003cp\u003e\nPartial model that implements the filters that are used to approximate the travel time of the actuators.\nThe signal \u003ccode\u003ey_actual\u003c/code\u003e is used to obtain the current position of the actuators.\n\u003c/p\u003e\n\u003c/html\u003e\""}]}}]}}}}}}}},"comment":{}}}}]}}},"comment":{}}}}]}}}}}}}]}